compai/__init__.py
compai/compai.py
compai-0.1.3.dist-info/LICENSE
compai-0.1.3.dist-info/WHEEL
compai-0.1.3.dist-info/METADATA
compai-0.1.3.dist-info/RECORD
