Metadata-Version: 2.1
Name: compai
Version: 0.1.3
Summary: Functional primitives for python
Home-page: https://github.com/frndmg/compai
License: MIT
Author: Fernando Martínez González
Author-email: frndmartinezglez@gmail.com
Requires-Python: >=3.6,<4.0
Classifier: License :: OSI Approved :: MIT License
Classifier: Programming Language :: Python :: 3
Classifier: Programming Language :: Python :: 3.6
Classifier: Programming Language :: Python :: 3.7
Classifier: Programming Language :: Python :: 3.8
Classifier: Programming Language :: Python :: 3.9
Provides-Extra: docs
Requires-Dist: importlib-metadata (>=3.7.0,<4.0.0); python_version < "3.7"
Requires-Dist: mkdocs (>=1.1.2,<2.0.0); extra == "docs"
Requires-Dist: mkdocs-material (>=7.0.4,<8.0.0); extra == "docs"
Requires-Dist: mkdocstrings (>=0.15.0,<0.16.0); extra == "docs"
Project-URL: Repository, https://github.com/frndmg/compai
